{
  "input_hash": "35cdfb4a97a0d1892b04a6c27bc55226cb931e1c84292a34527402e305f3c578",
  "dataset_name": "bao_compatibility",
  "processing_timestamp": "2025-10-23T14:12:31.547322+00:00",
  "environment_hash": "28f73e5ec49e78edadac0fd930337b0aa0ae2978967c644ef6e16d9238f87d95",
  "dataset": {
    "z": [
      0.32
    ],
    "observable": [
      8.88
    ],
    "uncertainty": [
      0.17
    ],
    "covariance": null,
    "metadata": {
      "dataset_type": "bao",
      "measurement_type": "isotropic",
      "source": "bao_compatibility_test",
      "citation": "",
      "version": "1.0",
      "processing_timestamp": "2025-10-23T22:12:31.546661",
      "n_redshift_bins": 1,
      "redshift_range": [
        0.32,
        0.32
      ],
      "survey": "unknown",
      "transformations_applied": [
        "unit_conversion_to_mpc",
        "survey_specific_corrections",
        "correlation_matrix_validation"
      ],
      "observable_description": "Isotropic BAO distance D_V/r_d",
      "n_measurements": 1,
      "n_points": 1
    }
  }
}